Workbook
Name ScenarioSelector: Assumptions!$B$2

Sheet Assumptions
A1: Financial model | B1: Value | C1: Unit | D1: Source | E1: Date | F1: Confidence | G1: Notes
A2: Scenario selector | B2: Base | D2: Choose Base, Upside, or Downside
A3: meta.venture | B3: strata | C3: text | D3: product/FINANCIAL_BRIEF_STRATA.md | E3: 2026-08-30 | F3: H
A5: meta.scenario | B5: base | C5: text | D5: product/FINANCIAL_BRIEF_STRATA.md | E5: 2026-08-30 | F5: H
A6: meta.currency | B6: USD | C6: iso-4217 | D6: brief | E6: 2026-08-30 | F6: H
A7: meta.start_month | B7: 2026-10 | C7: YYYY-MM | D7: joseleos in Strata channel 2026-08-30 04:47 (event d9d225ef) — launch in 6–8 weeks from 2026-08-30 | E7: 2026-08-30 | F7: M
A8: meta.horizon_months | B8: 36 | C8: months | D8: docs/FINANCIAL_MODEL_PLAN.md answer #1 (3-year default) — carried over pending confirmation | confirmed by joseleos 2026-08-30 15:23 | E8: 2026-08-30 | F8: M
A9: meta.opening_cash | B9: 10000 | C9: USD | D9: assumption: company cash at launch not yet stated by joseleos — PLACEHOLDER, please override | override: joseleos 2026-08-30 15:23 (event 7a9ad457) 'assume under $10,000' → modeled at the $10k ceiling | E9: 2026-08-30 | F9: L
A10: formation_legal.items[0].name | B10: Delaware Public Benefit Corporation formation (incl. 83(b), IP assignment) | C10: text | D10: stripe.com/atlas ($500) / clerky.com (~$800 formation + post-incorporation); HermesX wiki note 2026-06-27 says C Corp already forming — may already be spent | override: joseleos 2026-08-30 15:23 — entity is a PBC (state assumed Delaware; taxed as a C-Corp, same franchise tax) | E10: 2026-08-30 | F10: M
A11: formation_legal.items[0].amount | B11: 800 | C11: USD | D11: stripe.com/atlas ($500) / clerky.com (~$800 formation + post-incorporation); HermesX wiki note 2026-06-27 says C Corp already forming — may already be spent | Delaware PBC confirmed by joseleos 2026-08-30 15:28 (event 66e12ec9) | E11: 2026-08-30 | F11: M
A12: formation_legal.items[0].cadence | B12: one_time | C12: cadence | D12: stripe.com/atlas ($500) / clerky.com (~$800 formation + post-incorporation); HermesX wiki note 2026-06-27 says C Corp already forming — may already be spent | E12: 2026-08-30 | F12: H
A13: formation_legal.items[0].start_month | B13: 1 | C13: month | D13: stripe.com/atlas ($500) / clerky.com (~$800 formation + post-incorporation); HermesX wiki note 2026-06-27 says C Corp already forming — may already be spent | E13: 2026-08-30 | F13: M
A14: formation_legal.items[0].end_month | B14: 1 | C14: month | D14: stripe.com/atlas ($500) / clerky.com (~$800 formation + post-incorporation); HermesX wiki note 2026-06-27 says C Corp already forming — may already be spent | E14: 2026-08-30 | F14: M
A15: formation_legal.items[1].name | B15: Delaware registered agent | C15: text | D15: delawareregisteredagent.com / harvardbusiness services $50–$300/yr range | E15: 2026-08-30 | F15: M
A16: formation_legal.items[1].amount | B16: 150 | C16: USD | D16: delawareregisteredagent.com / harvardbusiness services $50–$300/yr range | Delaware PBC confirmed by joseleos 2026-08-30 15:28 (event 66e12ec9) | E16: 2026-08-30 | F16: M
A17: formation_legal.items[1].cadence | B17: annual | C17: cadence | D17: delawareregisteredagent.com / harvardbusiness services $50–$300/yr range | E17: 2026-08-30 | F17: H
A18: formation_legal.items[1].start_month | B18: 1 | C18: month | D18: delawareregisteredagent.com / harvardbusiness services $50–$300/yr range | E18: 2026-08-30 | F18: M
A19: formation_legal.items[1].end_month | B19: 36 | C19: month | D19: delawareregisteredagent.com / harvardbusiness services $50–$300/yr range | E19: 2026-08-30 | F19: M
A20: formation_legal.items[2].name | B20: Delaware franchise tax + annual report (assumed-par-value minimum) | C20: text | D20: corp.delaware.gov: $400 min tax (assumed par value method) + $50 report fee | E20: 2026-08-30 | F20: H
A21: formation_legal.items[2].amount | B21: 450 | C21: USD | D21: corp.delaware.gov: $400 min tax (assumed par value method) + $50 report fee | Delaware PBC confirmed by joseleos 2026-08-30 15:28 (event 66e12ec9) | E21: 2026-08-30 | F21: H
A22: formation_legal.items[2].cadence | B22: annual | C22: cadence | D22: corp.delaware.gov: $400 min tax (assumed par value method) + $50 report fee | E22: 2026-08-30 | F22: H
A23: formation_legal.items[2].start_month | B23: 6 | C23: month | D23: corp.delaware.gov: $400 min tax (assumed par value method) + $50 report fee | E23: 2026-08-30 | F23: H
A24: formation_legal.items[2].end_month | B24: 36 | C24: month | D24: corp.delaware.gov: $400 min tax (assumed par value method) + $50 report fee | E24: 2026-08-30 | F24: H
A25: formation_legal.items[3].name | B25: Texas foreign qualification (Form 301) | C25: text | D25: sos.state.tx.us fee schedule: $750 foreign for-profit corporation registration | E25: 2026-08-30 | F25: H
A26: formation_legal.items[3].amount | B26: 750 | C26: USD | D26: sos.state.tx.us fee schedule: $750 foreign for-profit corporation registration | Delaware PBC confirmed by joseleos 2026-08-30 15:28 (event 66e12ec9) | E26: 2026-08-30 | F26: H
A27: formation_legal.items[3].cadence | B27: one_time | C27: cadence | D27: sos.state.tx.us fee schedule: $750 foreign for-profit corporation registration | E27: 2026-08-30 | F27: H
A28: formation_legal.items[3].start_month | B28: 1 | C28: month | D28: sos.state.tx.us fee schedule: $750 foreign for-profit corporation registration | E28: 2026-08-30 | F28: H
A29: formation_legal.items[3].end_month | B29: 1 | C29: month | D29: sos.state.tx.us fee schedule: $750 foreign for-profit corporation registration | E29: 2026-08-30 | F29: H
A30: formation_legal.items[4].name | B30: Municipal pilot agreement + MSA/DPA templates (counsel) | C30: text | D30: assumption: GTM open question #3 says pilot agreement not yet drafted; municipal data terms + TX Public Information Act clauses | E30: 2026-08-30 | F30: L
A31: formation_legal.items[4].amount | B31: 2500 | C31: USD | D31: assumption: GTM open question #3 says pilot agreement not yet drafted; municipal data terms + TX Public Information Act clauses | E31: 2026-08-30 | F31: L
A32: formation_legal.items[4].cadence | B32: one_time | C32: cadence | D32: assumption: GTM open question #3 says pilot agreement not yet drafted; municipal data terms + TX Public Information Act clauses | E32: 2026-08-30 | F32: H
A33: formation_legal.items[4].start_month | B33: 1 | C33: month | D33: assumption: GTM open question #3 says pilot agreement not yet drafted; municipal data terms + TX Public Information Act clauses | E33: 2026-08-30 | F33: L
A34: formation_legal.items[4].end_month | B34: 1 | C34: month | D34: assumption: GTM open question #3 says pilot agreement not yet drafted; municipal data terms + TX Public Information Act clauses | E34: 2026-08-30 | F34: L
A35: formation_legal.items[5].name | B35: Trademark filing (USPTO 1 class + counsel) | C35: text | D35: uspto.gov: $350/class electronic filing fee (2025) + ~$1,000 counsel | E35: 2026-08-30 | F35: M
A36: formation_legal.items[5].amount | B36: 1350 | C36: USD | D36: uspto.gov: $350/class electronic filing fee (2025) + ~$1,000 counsel | E36: 2026-08-30 | F36: M
A37: formation_legal.items[5].cadence | B37: one_time | C37: cadence | D37: uspto.gov: $350/class electronic filing fee (2025) + ~$1,000 counsel | E37: 2026-08-30 | F37: H
A38: formation_legal.items[5].start_month | B38: 6 | C38: month | D38: uspto.gov: $350/class electronic filing fee (2025) + ~$1,000 counsel | E38: 2026-08-30 | F38: M
A39: formation_legal.items[5].end_month | B39: 6 | C39: month | D39: uspto.gov: $350/class electronic filing fee (2025) + ~$1,000 counsel | E39: 2026-08-30 | F39: M
A40: formation_legal.items[6].name | B40: Financing counsel reserve | C40: text | D40: Bootstrapped base case per joseleos (minimal budget until revenue or investment) — $0; add on override if a SAFE is raised | E40: 2026-08-30 | F40: H
A41: formation_legal.items[6].amount | B41: 0 | C41: USD | D41: Bootstrapped base case per joseleos (minimal budget until revenue or investment) — $0; add on override if a SAFE is raised | E41: 2026-08-30 | F41: H
A42: formation_legal.items[6].cadence | B42: one_time | C42: cadence | D42: Bootstrapped base case per joseleos (minimal budget until revenue or investment) — $0; add on override if a SAFE is raised | E42: 2026-08-30 | F42: H
A43: formation_legal.items[6].start_month | B43: 1 | C43: month | D43: Bootstrapped base case per joseleos (minimal budget until revenue or investment) — $0; add on override if a SAFE is raised | E43: 2026-08-30 | F43: H
A44: formation_legal.items[6].end_month | B44: 1 | C44: month | D44: Bootstrapped base case per joseleos (minimal budget until revenue or investment) — $0; add on override if a SAFE is raised | E44: 2026-08-30 | F44: H
A45: ga_ops.items[0].name | B45: Bookkeeping + accounting (outsourced) | C45: text | D45: assumption: Bench/Pilot starter tiers $300–$700/mo; low end while transactions are few | E45: 2026-08-30 | F45: M
A46: ga_ops.items[0].amount | B46: 300 | C46: USD | D46: assumption: Bench/Pilot starter tiers $300–$700/mo; low end while transactions are few | E46: 2026-08-30 | F46: M
A47: ga_ops.items[0].cadence | B47: monthly | C47: cadence | D47: assumption: Bench/Pilot starter tiers $300–$700/mo; low end while transactions are few | E47: 2026-08-30 | F47: H
A48: ga_ops.items[0].start_month | B48: 1 | C48: month | D48: assumption: Bench/Pilot starter tiers $300–$700/mo; low end while transactions are few | E48: 2026-08-30 | F48: M
A49: ga_ops.items[0].end_month | B49: 36 | C49: month | D49: assumption: Bench/Pilot starter tiers $300–$700/mo; low end while transactions are few | E49: 2026-08-30 | F49: M
A50: ga_ops.items[1].name | B50: Annual tax prep (federal 1120 + DE + TX franchise no-tax-due report) | C50: text | D50: assumption: small C-Corp return $1.5–2.5k; TX franchise tax no-tax-due threshold $2.47M (comptroller.texas.gov) | E50: 2026-08-30 | F50: M
A51: ga_ops.items[1].amount | B51: 2000 | C51: USD | D51: assumption: small C-Corp return $1.5–2.5k; TX franchise tax no-tax-due threshold $2.47M (comptroller.texas.gov) | E51: 2026-08-30 | F51: M
A52: ga_ops.items[1].cadence | B52: annual | C52: cadence | D52: assumption: small C-Corp return $1.5–2.5k; TX franchise tax no-tax-due threshold $2.47M (comptroller.texas.gov) | E52: 2026-08-30 | F52: H
A53: ga_ops.items[1].start_month | B53: 12 | C53: month | D53: assumption: small C-Corp return $1.5–2.5k; TX franchise tax no-tax-due threshold $2.47M (comptroller.texas.gov) | E53: 2026-08-30 | F53: M
A54: ga_ops.items[1].end_month | B54: 36 | C54: month | D54: assumption: small C-Corp return $1.5–2.5k; TX franchise tax no-tax-due threshold $2.47M (comptroller.texas.gov) | E54: 2026-08-30 | F54: M
A55: ga_ops.items[2].name | B55: Insurance: cyber liability $1M + tech E&O + GL | C55: text | D55: assumption: early-stage SaaS packages (Vouch/Embroker) $2–5k/yr; TX cities commonly require a certificate of insurance before pilot data access | E55: 2026-08-30 | F55: L
A56: ga_ops.items[2].amount | B56: 3600 | C56: USD | D56: assumption: early-stage SaaS packages (Vouch/Embroker) $2–5k/yr; TX cities commonly require a certificate of insurance before pilot data access | E56: 2026-08-30 | F56: L
A57: ga_ops.items[2].cadence | B57: annual | C57: cadence | D57: assumption: early-stage SaaS packages (Vouch/Embroker) $2–5k/yr; TX cities commonly require a certificate of insurance before pilot data access | E57: 2026-08-30 | F57: H
A58: ga_ops.items[2].start_month | B58: 1 | C58: month | D58: assumption: early-stage SaaS packages (Vouch/Embroker) $2–5k/yr; TX cities commonly require a certificate of insurance before pilot data access | E58: 2026-08-30 | F58: L
A59: ga_ops.items[2].end_month | B59: 36 | C59: month | D59: assumption: early-stage SaaS packages (Vouch/Embroker) $2–5k/yr; TX cities commonly require a certificate of insurance before pilot data access | E59: 2026-08-30 | F59: L
A60: ga_ops.items[3].name | B60: Software seats + domain + email + banking | C60: text | D60: assumption: Google Workspace, 1Password, Mercury (free), domain — per active person | E60: 2026-08-30 | F60: M
A61: ga_ops.items[3].amount | B61: 120 | C61: USD | D61: assumption: Google Workspace, 1Password, Mercury (free), domain — per active person | E61: 2026-08-30 | F61: M
A62: ga_ops.items[3].cadence | B62: monthly | C62: cadence | D62: assumption: Google Workspace, 1Password, Mercury (free), domain — per active person | E62: 2026-08-30 | F62: H
A63: ga_ops.items[3].start_month | B63: 1 | C63: month | D63: assumption: Google Workspace, 1Password, Mercury (free), domain — per active person | E63: 2026-08-30 | F63: M
A64: ga_ops.items[3].end_month | B64: 36 | C64: month | D64: assumption: Google Workspace, 1Password, Mercury (free), domain — per active person | E64: 2026-08-30 | F64: M
A65: ga_ops.items[4].name | B65: Payroll provider (Gusto) — starts with first paid employee | C65: text | D65: gusto.com Simple plan $40/mo + $6/person | E65: 2026-08-30 | F65: H
A66: ga_ops.items[4].amount | B66: 60 | C66: USD | D66: gusto.com Simple plan $40/mo + $6/person | E66: 2026-08-30 | F66: H
A67: ga_ops.items[4].cadence | B67: monthly | C67: cadence | D67: gusto.com Simple plan $40/mo + $6/person | E67: 2026-08-30 | F67: H
A68: ga_ops.items[4].start_month | B68: 28 | C68: month | D68: gusto.com Simple plan $40/mo + $6/person | E68: 2026-08-30 | F68: H
A69: ga_ops.items[4].end_month | B69: 36 | C69: month | D69: gusto.com Simple plan $40/mo + $6/person | E69: 2026-08-30 | F69: H
A70: ga_ops.items[5].name | B70: Remote stipend / coworking | C70: text | D70: joseleos in Strata channel 2026-08-30 04:47 (event d9d225ef) — minimal budget; $0 until funded | E70: 2026-08-30 | F70: H
A71: ga_ops.items[5].amount | B71: 0 | C71: USD | D71: joseleos in Strata channel 2026-08-30 04:47 (event d9d225ef) — minimal budget; $0 until funded | E71: 2026-08-30 | F71: H
A72: ga_ops.items[5].cadence | B72: monthly | C72: cadence | D72: joseleos in Strata channel 2026-08-30 04:47 (event d9d225ef) — minimal budget; $0 until funded | E72: 2026-08-30 | F72: H
A73: ga_ops.items[5].start_month | B73: 1 | C73: month | D73: joseleos in Strata channel 2026-08-30 04:47 (event d9d225ef) — minimal budget; $0 until funded | E73: 2026-08-30 | F73: H
A74: ga_ops.items[5].end_month | B74: 36 | C74: month | D74: joseleos in Strata channel 2026-08-30 04:47 (event d9d225ef) — minimal budget; $0 until funded | E74: 2026-08-30 | F74: H
A75: personnel.roster[0].role | B75: Founder / CEO + product (joseleos) | C75: text | D75: joseleos in Strata channel 2026-08-30 04:47 (event d9d225ef); base is memo-only (deferred) per FINANCIAL_MODEL_PLAN answer #2 | E75: 2026-08-30 | F75: M
A76: personnel.roster[0].headcount | B76: 1 | C76: FTE | D76: joseleos in Strata channel 2026-08-30 04:47 (event d9d225ef); base is memo-only (deferred) per FINANCIAL_MODEL_PLAN answer #2 | E76: 2026-08-30 | F76: M
A77: personnel.roster[0].start_month | B77: 1 | C77: month | D77: joseleos in Strata channel 2026-08-30 04:47 (event d9d225ef); base is memo-only (deferred) per FINANCIAL_MODEL_PLAN answer #2 | E77: 2026-08-30 | F77: M
A78: personnel.roster[0].end_month | B78: 36 | C78: month | D78: joseleos in Strata channel 2026-08-30 04:47 (event d9d225ef); base is memo-only (deferred) per FINANCIAL_MODEL_PLAN answer #2 | E78: 2026-08-30 | F78: M
A79: personnel.roster[0].annual_base | B79: 150000 | C79: USD/yr | D79: joseleos in Strata channel 2026-08-30 04:47 (event d9d225ef); base is memo-only (deferred) per FINANCIAL_MODEL_PLAN answer #2 | E79: 2026-08-30 | F79: M
A80: personnel.roster[0].employer_tax_pct | B80: 0.09 | C80: ratio | D80: FICA 7.65% (irs.gov Topic 751) + FUTA 0.6% + TX SUTA new-employer 2.7% on first $9k (twc.texas.gov) ≈ 9% blended | E80: 2026-08-30 | F80: M
A81: personnel.roster[0].benefits_pct | B81: 0.12 | C81: ratio | D81: assumption: small-employer health + 401k match, no equity accounting | E81: 2026-08-30 | F81: L
A82: personnel.roster[0].equipment | B82: 2500 | C82: USD one-time | D82: assumption: laptop + peripherals | E82: 2026-08-30 | F82: M
A83: personnel.roster[0].founder | B83: TRUE | C83: bool | D83: joseleos in Strata channel 2026-08-30 04:47 (event d9d225ef); base is memo-only (deferred) per FINANCIAL_MODEL_PLAN answer #2 | E83: 2026-08-30 | F83: H
A84: personnel.roster[0].defer_until_funding | B84: TRUE | C84: bool | D84: docs/FINANCIAL_MODEL_PLAN.md answers 2026-08-30 (founder pay deferred until funding) — carried over to Strata pending confirmation | confirmed by joseleos 2026-08-30 15:23 | E84: 2026-08-30 | F84: M
A85: personnel.roster[1].role | B85: Contract full-stack engineer, 0.5 FTE (1099; no payroll burden) | C85: text | D85: assumption: ~$12k/mo full-time-equivalent US contractor rate at half time; ends the month before the FTE hire | E85: 2026-08-30 | F85: M
A86: personnel.roster[1].headcount | B86: 1 | C86: FTE | D86: assumption: ~$12k/mo full-time-equivalent US contractor rate at half time; ends the month before the FTE hire | E86: 2026-08-30 | F86: M
A87: personnel.roster[1].start_month | B87: 13 | C87: month | D87: assumption: ~$12k/mo full-time-equivalent US contractor rate at half time; ends the month before the FTE hire | E87: 2026-08-30 | F87: M
A88: personnel.roster[1].end_month | B88: 27 | C88: month | D88: assumption: ~$12k/mo full-time-equivalent US contractor rate at half time; ends the month before the FTE hire | E88: 2026-08-30 | F88: M
A89: personnel.roster[1].annual_base | B89: 72000 | C89: USD/yr | D89: assumption: ~$12k/mo full-time-equivalent US contractor rate at half time; ends the month before the FTE hire | E89: 2026-08-30 | F89: M
A90: personnel.roster[1].employer_tax_pct | B90: 0 | C90: ratio | D90: 1099 contractor — no employer payroll tax | E90: 2026-08-30 | F90: H
A91: personnel.roster[1].benefits_pct | B91: 0 | C91: ratio | D91: 1099 contractor — no benefits | E91: 2026-08-30 | F91: H
A92: personnel.roster[1].equipment | B92: 0 | C92: USD one-time | D92: contractor supplies own equipment | E92: 2026-08-30 | F92: H
A93: personnel.roster[1].founder | B93: FALSE | C93: bool | D93: assumption: ~$12k/mo full-time-equivalent US contractor rate at half time; ends the month before the FTE hire | E93: 2026-08-30 | F93: H
A94: personnel.roster[1].defer_until_funding | B94: FALSE | C94: bool | D94: docs/FINANCIAL_MODEL_PLAN.md answers 2026-08-30 (founder pay deferred until funding) — carried over to Strata pending confirmation | E94: 2026-08-30 | F94: M
A95: personnel.roster[2].role | B95: Full-stack engineer, FTE (hired once gross-margin cash covers ≈$13.1k/mo loaded cost ≈ 18 paying Core cities) | C95: text | D95: assumption: Texas remote senior full-stack $120–150k base (levels.fyi/BuiltIn Austin 2025 ranges); timing rule from FINANCIAL_BRIEF_STRATA.md | E95: 2026-08-30 | F95: M
A96: personnel.roster[2].headcount | B96: 1 | C96: FTE | D96: assumption: Texas remote senior full-stack $120–150k base (levels.fyi/BuiltIn Austin 2025 ranges); timing rule from FINANCIAL_BRIEF_STRATA.md | E96: 2026-08-30 | F96: M
A97: personnel.roster[2].start_month | B97: 28 | C97: month | D97: assumption: Texas remote senior full-stack $120–150k base (levels.fyi/BuiltIn Austin 2025 ranges); timing rule from FINANCIAL_BRIEF_STRATA.md | E97: 2026-08-30 | F97: M
A98: personnel.roster[2].end_month | B98: 36 | C98: month | D98: assumption: Texas remote senior full-stack $120–150k base (levels.fyi/BuiltIn Austin 2025 ranges); timing rule from FINANCIAL_BRIEF_STRATA.md | E98: 2026-08-30 | F98: M
A99: personnel.roster[2].annual_base | B99: 130000 | C99: USD/yr | D99: assumption: Texas remote senior full-stack $120–150k base (levels.fyi/BuiltIn Austin 2025 ranges); timing rule from FINANCIAL_BRIEF_STRATA.md | E99: 2026-08-30 | F99: M
A100: personnel.roster[2].employer_tax_pct | B100: 0.09 | C100: ratio | D100: FICA 7.65% (irs.gov Topic 751) + FUTA 0.6% + TX SUTA new-employer 2.7% on first $9k (twc.texas.gov) ≈ 9% blended | E100: 2026-08-30 | F100: M
A101: personnel.roster[2].benefits_pct | B101: 0.12 | C101: ratio | D101: assumption: small-employer health + 401k match, no equity accounting | E101: 2026-08-30 | F101: L
...

Sheet Scenarios
A1: Metric | B1: Base | C1: Upside | D1: Downside
A2: total_revenue | B2: 378843.46 | C2: 922560.21 | D2: 107510.69
A3: ending_cash | B3: 31600.26 | C3: 309645.48 | D3: -4471.88
A4: capital_need_to_break_even | B4: 29068.73 | C4: 32738.39 | D4: 31556.91
A5: break_even_month | B5: 7 | C5: 4 | D5: 15
A6: gross_margin_pct | B6: 0.89 | C6: 0.91 | D6: 0.79

Sheet Revenue
A1: Month | B1: Active logos | C1: New logos | D1: Revenue | E1: COGS | F1: Gross profit
A2: 2026-10 | B2: 0.35 | C2: 0.35 | D2: =CHOOSE(MATCH(ScenarioSelector,{"Base","Upside","Downside"},0),280,458.33,120) -> 280 | E2: =CHOOSE(MATCH(ScenarioSelector,{"Base","Upside","Downside"},0),34.65,43.75,25.6) -> 34.65 | F2: =D2-E2 -> 245.35
A3: 2026-11 | B3: 0.72 | C3: 0.37 | D3: =CHOOSE(MATCH(ScenarioSelector,{"Base","Upside","Downside"},0),574.65,953.01,242.56) -> 574.65 | E3: =CHOOSE(MATCH(ScenarioSelector,{"Base","Upside","Downside"},0),70.89,90.57,51.67) -> 70.89 | F3: =D3-E3 -> 503.76
A4: 2026-12 | B4: 1.1 | C4: 0.39 | D4: =CHOOSE(MATCH(ScenarioSelector,{"Base","Upside","Downside"},0),884.75,1486.82,367.77) -> 884.75 | E4: =CHOOSE(MATCH(ScenarioSelector,{"Base","Upside","Downside"},0),108.82,140.68,78.24) -> 108.82 | F4: =D4-E4 -> 775.94
A5: 2027-01 | B5: 1.5 | C5: 0.41 | D5: =CHOOSE(MATCH(ScenarioSelector,{"Base","Upside","Downside"},0),1211.14,2062.79,495.74) -> 1211.14 | E5: =CHOOSE(MATCH(ScenarioSelector,{"Base","Upside","Downside"},0),148.5,194.33,105.31) -> 148.5 | F5: =D5-E5 -> 1062.64
A6: 2027-02 | B6: 1.91 | C6: 0.43 | D6: =CHOOSE(MATCH(ScenarioSelector,{"Base","Upside","Downside"},0),1554.7,2684.15,626.55) -> 1554.7 | E6: =CHOOSE(MATCH(ScenarioSelector,{"Base","Upside","Downside"},0),190.04,251.76,132.91) -> 190.04 | F6: =D6-E6 -> 1364.66
A7: 2027-03 | B7: 2.35 | C7: 0.45 | D7: =CHOOSE(MATCH(ScenarioSelector,{"Base","Upside","Downside"},0),1916.36,3354.4,760.32) -> 1916.36 | E7: =CHOOSE(MATCH(ScenarioSelector,{"Base","Upside","Downside"},0),233.53,313.26,161.06) -> 233.53 | F7: =D7-E7 -> 1682.83
A8: 2027-04 | B8: 2.8 | C8: 0.47 | D8: =CHOOSE(MATCH(ScenarioSelector,{"Base","Upside","Downside"},0),2297.12,4077.3,897.15) -> 2297.12 | E8: =CHOOSE(MATCH(ScenarioSelector,{"Base","Upside","Downside"},0),279.08,379.12,189.77) -> 279.08 | F8: =D8-E8 -> 2018.04
A9: 2027-05 | B9: 3.28 | C9: 0.49 | D9: =CHOOSE(MATCH(ScenarioSelector,{"Base","Upside","Downside"},0),2698,4856.89,1037.15) -> 2698 | E9: =CHOOSE(MATCH(ScenarioSelector,{"Base","Upside","Downside"},0),326.78,449.66,219.07) -> 326.78 | F9: =D9-E9 -> 2371.22
A10: 2027-06 | B10: 3.78 | C10: 0.52 | D10: =CHOOSE(MATCH(ScenarioSelector,{"Base","Upside","Downside"},0),3120.11,5697.55,1180.43) -> 3120.11 | E10: =CHOOSE(MATCH(ScenarioSelector,{"Base","Upside","Downside"},0),376.75,525.21,248.99) -> 376.75 | F10: =D10-E10 -> 2743.35
A11: 2027-07 | B11: 4.3 | C11: 0.54 | D11: =CHOOSE(MATCH(ScenarioSelector,{"Base","Upside","Downside"},0),3564.58,6603.97,1327.11) -> 3564.58 | E11: =CHOOSE(MATCH(ScenarioSelector,{"Base","Upside","Downside"},0),429.11,606.13,279.53) -> 429.11 | F11: =D11-E11 -> 3135.47
A12: 2027-08 | B12: 4.84 | C12: 0.57 | D12: =CHOOSE(MATCH(ScenarioSelector,{"Base","Upside","Downside"},0),4032.65,7581.2,1477.3) -> 4032.65 | E12: =CHOOSE(MATCH(ScenarioSelector,{"Base","Upside","Downside"},0),483.98,692.83,310.72) -> 483.98 | F12: =D12-E12 -> 3548.67
A13: 2027-09 | B13: 5.41 | C13: 0.6 | D13: =CHOOSE(MATCH(ScenarioSelector,{"Base","Upside","Downside"},0),4525.58,8634.7,1631.13) -> 4525.58 | E13: =CHOOSE(MATCH(ScenarioSelector,{"Base","Upside","Downside"},0),541.48,785.72,342.6) -> 541.48 | F13: =D13-E13 -> 3984.1
A14: 2027-10 | B14: 6.01 | C14: 0.63 | D14: =CHOOSE(MATCH(ScenarioSelector,{"Base","Upside","Downside"},0),5044.74,9770.33,1788.73) -> 5044.74 | E14: =CHOOSE(MATCH(ScenarioSelector,{"Base","Upside","Downside"},0),601.76,885.25,375.17) -> 601.76 | F14: =D14-E14 -> 4442.97
A15: 2027-11 | B15: 6.63 | C15: 0.66 | D15: =CHOOSE(MATCH(ScenarioSelector,{"Base","Upside","Downside"},0),5591.54,10994.41,1950.23) -> 5591.54 | E15: =CHOOSE(MATCH(ScenarioSelector,{"Base","Upside","Downside"},0),664.96,991.9,408.46) -> 664.96 | F15: =D15-E15 -> 4926.57
A16: 2027-12 | B16: 7.28 | C16: 0.69 | D16: =CHOOSE(MATCH(ScenarioSelector,{"Base","Upside","Downside"},0),6167.48,12313.74,2115.77) -> 6167.48 | E16: =CHOOSE(MATCH(ScenarioSelector,{"Base","Upside","Downside"},0),731.23,1106.19,442.5) -> 731.23 | F16: =D16-E16 -> 5436.25
A17: 2028-01 | B17: 7.97 | C17: 0.73 | D17: =CHOOSE(MATCH(ScenarioSelector,{"Base","Upside","Downside"},0),6774.16,13735.65,2285.47) -> 6774.16 | E17: =CHOOSE(MATCH(ScenarioSelector,{"Base","Upside","Downside"},0),800.73,1228.67,477.32) -> 800.73 | F17: =D17-E17 -> 5973.43
A18: 2028-02 | B18: 8.68 | C18: 0.76 | D18: =CHOOSE(MATCH(ScenarioSelector,{"Base","Upside","Downside"},0),7413.24,15268.02,2459.49) -> 7413.24 | E18: =CHOOSE(MATCH(ScenarioSelector,{"Base","Upside","Downside"},0),873.62,1359.94,512.94) -> 873.62 | F18: =D18-E18 -> 6539.62
A19: 2028-03 | B19: 9.43 | C19: 0.8 | D19: =CHOOSE(MATCH(ScenarioSelector,{"Base","Upside","Downside"},0),8086.47,16919.36,2637.98) -> 8086.47 | E19: =CHOOSE(MATCH(ScenarioSelector,{"Base","Upside","Downside"},0),950.07,1500.64,549.39) -> 950.07 | F19: =D19-E19 -> 7136.4
A20: 2028-04 | B20: 10.22 | C20: 0.84 | D20: =CHOOSE(MATCH(ScenarioSelector,{"Base","Upside","Downside"},0),8795.72,18698.8,2821.08) -> 8795.72 | E20: =CHOOSE(MATCH(ScenarioSelector,{"Base","Upside","Downside"},0),1030.28,1651.44,586.69) -> 1030.28 | F20: =D20-E20 -> 7765.44
A21: 2028-05 | B21: 11.04 | C21: 0.88 | D21: =CHOOSE(MATCH(ScenarioSelector,{"Base","Upside","Downside"},0),9542.94,20616.22,3008.95) -> 9542.94 | E21: =CHOOSE(MATCH(ScenarioSelector,{"Base","Upside","Downside"},0),1114.43,1813.1,624.88) -> 1114.43 | F21: =D21-E21 -> 8428.51
A22: 2028-06 | B22: 11.9 | C22: 0.93 | D22: =CHOOSE(MATCH(ScenarioSelector,{"Base","Upside","Downside"},0),10330.18,22682.2,3201.76) -> 10330.18 | E22: =CHOOSE(MATCH(ScenarioSelector,{"Base","Upside","Downside"},0),1202.73,1986.39,663.98) -> 1202.73 | F22: =D22-E22 -> 9127.46
A23: 2028-07 | B23: 12.81 | C23: 0.98 | D23: =CHOOSE(MATCH(ScenarioSelector,{"Base","Upside","Downside"},0),11159.64,24908.19,3399.67) -> 11159.64 | E23: =CHOOSE(MATCH(ScenarioSelector,{"Base","Upside","Downside"},0),1295.38,2172.17,704.03) -> 1295.38 | F23: =D23-E23 -> 9864.25
A24: 2028-08 | B24: 13.75 | C24: 1.02 | D24: =CHOOSE(MATCH(ScenarioSelector,{"Base","Upside","Downside"},0),12033.59,27306.49,3602.85) -> 12033.59 | E24: =CHOOSE(MATCH(ScenarioSelector,{"Base","Upside","Downside"},0),1392.63,2371.33,745.06) -> 1392.63 | F24: =D24-E24 -> 10640.96
A25: 2028-09 | B25: 14.75 | C25: 1.08 | D25: =CHOOSE(MATCH(ScenarioSelector,{"Base","Upside","Downside"},0),12954.45,29890.33,3811.49) -> 12954.45 | E25: =CHOOSE(MATCH(ScenarioSelector,{"Base","Upside","Downside"},0),1494.69,2584.85,787.09) -> 1494.69 | F25: =D25-E25 -> 11459.76

Sheet Headcount
A1: Month | B1: Headcount | C1: Cash personnel | D1: Deferred founder comp
A2: 2026-10 | B2: =CHOOSE(MATCH(ScenarioSelector,{"Base","Upside","Downside"},0),1,1,1) -> 1 | C2: =CHOOSE(MATCH(ScenarioSelector,{"Base","Upside","Downside"},0),0,0,0) -> 0 | D2: =CHOOSE(MATCH(ScenarioSelector,{"Base","Upside","Downside"},0),17625,17625,17625) -> 17625
A3: 2026-11 | B3: =CHOOSE(MATCH(ScenarioSelector,{"Base","Upside","Downside"},0),1,1,1) -> 1 | C3: =CHOOSE(MATCH(ScenarioSelector,{"Base","Upside","Downside"},0),0,0,0) -> 0 | D3: =CHOOSE(MATCH(ScenarioSelector,{"Base","Upside","Downside"},0),15125,15125,15125) -> 15125
A4: 2026-12 | B4: =CHOOSE(MATCH(ScenarioSelector,{"Base","Upside","Downside"},0),1,1,1) -> 1 | C4: =CHOOSE(MATCH(ScenarioSelector,{"Base","Upside","Downside"},0),0,0,0) -> 0 | D4: =CHOOSE(MATCH(ScenarioSelector,{"Base","Upside","Downside"},0),15125,15125,15125) -> 15125
A5: 2027-01 | B5: =CHOOSE(MATCH(ScenarioSelector,{"Base","Upside","Downside"},0),1,1,1) -> 1 | C5: =CHOOSE(MATCH(ScenarioSelector,{"Base","Upside","Downside"},0),0,0,0) -> 0 | D5: =CHOOSE(MATCH(ScenarioSelector,{"Base","Upside","Downside"},0),15125,15125,15125) -> 15125
A6: 2027-02 | B6: =CHOOSE(MATCH(ScenarioSelector,{"Base","Upside","Downside"},0),1,1,1) -> 1 | C6: =CHOOSE(MATCH(ScenarioSelector,{"Base","Upside","Downside"},0),0,0,0) -> 0 | D6: =CHOOSE(MATCH(ScenarioSelector,{"Base","Upside","Downside"},0),15125,15125,15125) -> 15125
A7: 2027-03 | B7: =CHOOSE(MATCH(ScenarioSelector,{"Base","Upside","Downside"},0),1,1,1) -> 1 | C7: =CHOOSE(MATCH(ScenarioSelector,{"Base","Upside","Downside"},0),0,0,0) -> 0 | D7: =CHOOSE(MATCH(ScenarioSelector,{"Base","Upside","Downside"},0),15125,15125,15125) -> 15125
A8: 2027-04 | B8: =CHOOSE(MATCH(ScenarioSelector,{"Base","Upside","Downside"},0),1,2,1) -> 1 | C8: =CHOOSE(MATCH(ScenarioSelector,{"Base","Upside","Downside"},0),0,6000,0) -> 0 | D8: =CHOOSE(MATCH(ScenarioSelector,{"Base","Upside","Downside"},0),15125,15125,15125) -> 15125
A9: 2027-05 | B9: =CHOOSE(MATCH(ScenarioSelector,{"Base","Upside","Downside"},0),1,2,1) -> 1 | C9: =CHOOSE(MATCH(ScenarioSelector,{"Base","Upside","Downside"},0),0,6000,0) -> 0 | D9: =CHOOSE(MATCH(ScenarioSelector,{"Base","Upside","Downside"},0),15125,15125,15125) -> 15125
A10: 2027-06 | B10: =CHOOSE(MATCH(ScenarioSelector,{"Base","Upside","Downside"},0),1,2,1) -> 1 | C10: =CHOOSE(MATCH(ScenarioSelector,{"Base","Upside","Downside"},0),0,6000,0) -> 0 | D10: =CHOOSE(MATCH(ScenarioSelector,{"Base","Upside","Downside"},0),15125,15125,15125) -> 15125
A11: 2027-07 | B11: =CHOOSE(MATCH(ScenarioSelector,{"Base","Upside","Downside"},0),1,2,1) -> 1 | C11: =CHOOSE(MATCH(ScenarioSelector,{"Base","Upside","Downside"},0),0,6000,0) -> 0 | D11: =CHOOSE(MATCH(ScenarioSelector,{"Base","Upside","Downside"},0),15125,15125,15125) -> 15125
A12: 2027-08 | B12: =CHOOSE(MATCH(ScenarioSelector,{"Base","Upside","Downside"},0),1,2,1) -> 1 | C12: =CHOOSE(MATCH(ScenarioSelector,{"Base","Upside","Downside"},0),0,6000,0) -> 0 | D12: =CHOOSE(MATCH(ScenarioSelector,{"Base","Upside","Downside"},0),15125,15125,15125) -> 15125
A13: 2027-09 | B13: =CHOOSE(MATCH(ScenarioSelector,{"Base","Upside","Downside"},0),1,2,1) -> 1 | C13: =CHOOSE(MATCH(ScenarioSelector,{"Base","Upside","Downside"},0),0,6000,0) -> 0 | D13: =CHOOSE(MATCH(ScenarioSelector,{"Base","Upside","Downside"},0),15125,15125,15125) -> 15125
A14: 2027-10 | B14: =CHOOSE(MATCH(ScenarioSelector,{"Base","Upside","Downside"},0),2,2,1) -> 2 | C14: =CHOOSE(MATCH(ScenarioSelector,{"Base","Upside","Downside"},0),6000,6000,0) -> 6000 | D14: =CHOOSE(MATCH(ScenarioSelector,{"Base","Upside","Downside"},0),15125,15125,15125) -> 15125
A15: 2027-11 | B15: =CHOOSE(MATCH(ScenarioSelector,{"Base","Upside","Downside"},0),2,2,1) -> 2 | C15: =CHOOSE(MATCH(ScenarioSelector,{"Base","Upside","Downside"},0),6000,6000,0) -> 6000 | D15: =CHOOSE(MATCH(ScenarioSelector,{"Base","Upside","Downside"},0),15125,15125,15125) -> 15125
A16: 2027-12 | B16: =CHOOSE(MATCH(ScenarioSelector,{"Base","Upside","Downside"},0),2,2,1) -> 2 | C16: =CHOOSE(MATCH(ScenarioSelector,{"Base","Upside","Downside"},0),6000,6000,0) -> 6000 | D16: =CHOOSE(MATCH(ScenarioSelector,{"Base","Upside","Downside"},0),15125,15125,15125) -> 15125
A17: 2028-01 | B17: =CHOOSE(MATCH(ScenarioSelector,{"Base","Upside","Downside"},0),2,2,1) -> 2 | C17: =CHOOSE(MATCH(ScenarioSelector,{"Base","Upside","Downside"},0),6000,15608.33,0) -> 6000 | D17: =CHOOSE(MATCH(ScenarioSelector,{"Base","Upside","Downside"},0),15125,15125,15125) -> 15125
A18: 2028-02 | B18: =CHOOSE(MATCH(ScenarioSelector,{"Base","Upside","Downside"},0),2,2,1) -> 2 | C18: =CHOOSE(MATCH(ScenarioSelector,{"Base","Upside","Downside"},0),6000,13108.33,0) -> 6000 | D18: =CHOOSE(MATCH(ScenarioSelector,{"Base","Upside","Downside"},0),15125,15125,15125) -> 15125
A19: 2028-03 | B19: =CHOOSE(MATCH(ScenarioSelector,{"Base","Upside","Downside"},0),2,2,1) -> 2 | C19: =CHOOSE(MATCH(ScenarioSelector,{"Base","Upside","Downside"},0),6000,13108.33,0) -> 6000 | D19: =CHOOSE(MATCH(ScenarioSelector,{"Base","Upside","Downside"},0),15125,15125,15125) -> 15125
A20: 2028-04 | B20: =CHOOSE(MATCH(ScenarioSelector,{"Base","Upside","Downside"},0),2,2,1) -> 2 | C20: =CHOOSE(MATCH(ScenarioSelector,{"Base","Upside","Downside"},0),6000,13108.33,0) -> 6000 | D20: =CHOOSE(MATCH(ScenarioSelector,{"Base","Upside","Downside"},0),15125,15125,15125) -> 15125
A21: 2028-05 | B21: =CHOOSE(MATCH(ScenarioSelector,{"Base","Upside","Downside"},0),2,2,1) -> 2 | C21: =CHOOSE(MATCH(ScenarioSelector,{"Base","Upside","Downside"},0),6000,13108.33,0) -> 6000 | D21: =CHOOSE(MATCH(ScenarioSelector,{"Base","Upside","Downside"},0),15125,15125,15125) -> 15125
A22: 2028-06 | B22: =CHOOSE(MATCH(ScenarioSelector,{"Base","Upside","Downside"},0),2,2,1) -> 2 | C22: =CHOOSE(MATCH(ScenarioSelector,{"Base","Upside","Downside"},0),6000,13108.33,0) -> 6000 | D22: =CHOOSE(MATCH(ScenarioSelector,{"Base","Upside","Downside"},0),15125,15125,15125) -> 15125
A23: 2028-07 | B23: =CHOOSE(MATCH(ScenarioSelector,{"Base","Upside","Downside"},0),2,2,1) -> 2 | C23: =CHOOSE(MATCH(ScenarioSelector,{"Base","Upside","Downside"},0),6000,13108.33,0) -> 6000 | D23: =CHOOSE(MATCH(ScenarioSelector,{"Base","Upside","Downside"},0),15125,15125,15125) -> 15125
A24: 2028-08 | B24: =CHOOSE(MATCH(ScenarioSelector,{"Base","Upside","Downside"},0),2,2,1) -> 2 | C24: =CHOOSE(MATCH(ScenarioSelector,{"Base","Upside","Downside"},0),6000,13108.33,0) -> 6000 | D24: =CHOOSE(MATCH(ScenarioSelector,{"Base","Upside","Downside"},0),15125,15125,15125) -> 15125
A25: 2028-09 | B25: =CHOOSE(MATCH(ScenarioSelector,{"Base","Upside","Downside"},0),2,2,1) -> 2 | C25: =CHOOSE(MATCH(ScenarioSelector,{"Base","Upside","Downside"},0),6000,13108.33,0) -> 6000 | D25: =CHOOSE(MATCH(ScenarioSelector,{"Base","Upside","Downside"},0),15125,15125,15125) -> 15125

Sheet OpEx
A1: Month | B1: Formation/legal | C1: G&A / ops | D1: R&D | E1: Sales & marketing | F1: Total OpEx
A2: 2026-10 | B2: =CHOOSE(MATCH(ScenarioSelector,{"Base","Upside","Downside"},0),4200,4200,4200) -> 4200 | C2: =CHOOSE(MATCH(ScenarioSelector,{"Base","Upside","Downside"},0),4020,4020,4020) -> 4020 | D2: =CHOOSE(MATCH(ScenarioSelector,{"Base","Upside","Downside"},0),350,350,350) -> 350 | E2: =CHOOSE(MATCH(ScenarioSelector,{"Base","Upside","Downside"},0),600,600,600) -> 600 | F2: =SUM(B2:E2) -> 9170
A3: 2026-11 | B3: =CHOOSE(MATCH(ScenarioSelector,{"Base","Upside","Downside"},0),0,0,0) -> 0 | C3: =CHOOSE(MATCH(ScenarioSelector,{"Base","Upside","Downside"},0),420,420,420) -> 420 | D3: =CHOOSE(MATCH(ScenarioSelector,{"Base","Upside","Downside"},0),4350,4350,4350) -> 4350 | E3: =CHOOSE(MATCH(ScenarioSelector,{"Base","Upside","Downside"},0),5100,5100,5100) -> 5100 | F3: =SUM(B3:E3) -> 9870
A4: 2026-12 | B4: =CHOOSE(MATCH(ScenarioSelector,{"Base","Upside","Downside"},0),0,0,0) -> 0 | C4: =CHOOSE(MATCH(ScenarioSelector,{"Base","Upside","Downside"},0),420,420,420) -> 420 | D4: =CHOOSE(MATCH(ScenarioSelector,{"Base","Upside","Downside"},0),350,350,350) -> 350 | E4: =CHOOSE(MATCH(ScenarioSelector,{"Base","Upside","Downside"},0),600,600,600) -> 600 | F4: =SUM(B4:E4) -> 1370
A5: 2027-01 | B5: =CHOOSE(MATCH(ScenarioSelector,{"Base","Upside","Downside"},0),0,0,0) -> 0 | C5: =CHOOSE(MATCH(ScenarioSelector,{"Base","Upside","Downside"},0),420,420,420) -> 420 | D5: =CHOOSE(MATCH(ScenarioSelector,{"Base","Upside","Downside"},0),350,350,350) -> 350 | E5: =CHOOSE(MATCH(ScenarioSelector,{"Base","Upside","Downside"},0),600,600,600) -> 600 | F5: =SUM(B5:E5) -> 1370
A6: 2027-02 | B6: =CHOOSE(MATCH(ScenarioSelector,{"Base","Upside","Downside"},0),0,0,0) -> 0 | C6: =CHOOSE(MATCH(ScenarioSelector,{"Base","Upside","Downside"},0),420,420,420) -> 420 | D6: =CHOOSE(MATCH(ScenarioSelector,{"Base","Upside","Downside"},0),350,350,350) -> 350 | E6: =CHOOSE(MATCH(ScenarioSelector,{"Base","Upside","Downside"},0),600,600,600) -> 600 | F6: =SUM(B6:E6) -> 1370
A7: 2027-03 | B7: =CHOOSE(MATCH(ScenarioSelector,{"Base","Upside","Downside"},0),1800,1800,1800) -> 1800 | C7: =CHOOSE(MATCH(ScenarioSelector,{"Base","Upside","Downside"},0),420,420,420) -> 420 | D7: =CHOOSE(MATCH(ScenarioSelector,{"Base","Upside","Downside"},0),350,350,350) -> 350 | E7: =CHOOSE(MATCH(ScenarioSelector,{"Base","Upside","Downside"},0),600,600,600) -> 600 | F7: =SUM(B7:E7) -> 3170
A8: 2027-04 | B8: =CHOOSE(MATCH(ScenarioSelector,{"Base","Upside","Downside"},0),0,0,0) -> 0 | C8: =CHOOSE(MATCH(ScenarioSelector,{"Base","Upside","Downside"},0),420,420,420) -> 420 | D8: =CHOOSE(MATCH(ScenarioSelector,{"Base","Upside","Downside"},0),350,350,350) -> 350 | E8: =CHOOSE(MATCH(ScenarioSelector,{"Base","Upside","Downside"},0),600,600,600) -> 600 | F8: =SUM(B8:E8) -> 1370
A9: 2027-05 | B9: =CHOOSE(MATCH(ScenarioSelector,{"Base","Upside","Downside"},0),0,0,0) -> 0 | C9: =CHOOSE(MATCH(ScenarioSelector,{"Base","Upside","Downside"},0),420,420,420) -> 420 | D9: =CHOOSE(MATCH(ScenarioSelector,{"Base","Upside","Downside"},0),350,350,350) -> 350 | E9: =CHOOSE(MATCH(ScenarioSelector,{"Base","Upside","Downside"},0),600,600,600) -> 600 | F9: =SUM(B9:E9) -> 1370
A10: 2027-06 | B10: =CHOOSE(MATCH(ScenarioSelector,{"Base","Upside","Downside"},0),0,0,0) -> 0 | C10: =CHOOSE(MATCH(ScenarioSelector,{"Base","Upside","Downside"},0),420,420,420) -> 420 | D10: =CHOOSE(MATCH(ScenarioSelector,{"Base","Upside","Downside"},0),350,350,350) -> 350 | E10: =CHOOSE(MATCH(ScenarioSelector,{"Base","Upside","Downside"},0),600,600,600) -> 600 | F10: =SUM(B10:E10) -> 1370
A11: 2027-07 | B11: =CHOOSE(MATCH(ScenarioSelector,{"Base","Upside","Downside"},0),0,0,0) -> 0 | C11: =CHOOSE(MATCH(ScenarioSelector,{"Base","Upside","Downside"},0),420,420,420) -> 420 | D11: =CHOOSE(MATCH(ScenarioSelector,{"Base","Upside","Downside"},0),350,350,350) -> 350 | E11: =CHOOSE(MATCH(ScenarioSelector,{"Base","Upside","Downside"},0),600,600,600) -> 600 | F11: =SUM(B11:E11) -> 1370
A12: 2027-08 | B12: =CHOOSE(MATCH(ScenarioSelector,{"Base","Upside","Downside"},0),0,0,0) -> 0 | C12: =CHOOSE(MATCH(ScenarioSelector,{"Base","Upside","Downside"},0),420,420,420) -> 420 | D12: =CHOOSE(MATCH(ScenarioSelector,{"Base","Upside","Downside"},0),350,350,350) -> 350 | E12: =CHOOSE(MATCH(ScenarioSelector,{"Base","Upside","Downside"},0),600,600,600) -> 600 | F12: =SUM(B12:E12) -> 1370
A13: 2027-09 | B13: =CHOOSE(MATCH(ScenarioSelector,{"Base","Upside","Downside"},0),0,0,0) -> 0 | C13: =CHOOSE(MATCH(ScenarioSelector,{"Base","Upside","Downside"},0),2420,2420,2420) -> 2420 | D13: =CHOOSE(MATCH(ScenarioSelector,{"Base","Upside","Downside"},0),350,350,350) -> 350 | E13: =CHOOSE(MATCH(ScenarioSelector,{"Base","Upside","Downside"},0),600,600,600) -> 600 | F13: =SUM(B13:E13) -> 3370
A14: 2027-10 | B14: =CHOOSE(MATCH(ScenarioSelector,{"Base","Upside","Downside"},0),150,150,150) -> 150 | C14: =CHOOSE(MATCH(ScenarioSelector,{"Base","Upside","Downside"},0),4020,4020,4020) -> 4020 | D14: =CHOOSE(MATCH(ScenarioSelector,{"Base","Upside","Downside"},0),350,350,350) -> 350 | E14: =CHOOSE(MATCH(ScenarioSelector,{"Base","Upside","Downside"},0),850,850,850) -> 850 | F14: =SUM(B14:E14) -> 5370
A15: 2027-11 | B15: =CHOOSE(MATCH(ScenarioSelector,{"Base","Upside","Downside"},0),0,0,0) -> 0 | C15: =CHOOSE(MATCH(ScenarioSelector,{"Base","Upside","Downside"},0),420,420,420) -> 420 | D15: =CHOOSE(MATCH(ScenarioSelector,{"Base","Upside","Downside"},0),6350,6350,6350) -> 6350 | E15: =CHOOSE(MATCH(ScenarioSelector,{"Base","Upside","Downside"},0),5350,6850,3850) -> 5350 | F15: =SUM(B15:E15) -> 12120
A16: 2027-12 | B16: =CHOOSE(MATCH(ScenarioSelector,{"Base","Upside","Downside"},0),0,0,0) -> 0 | C16: =CHOOSE(MATCH(ScenarioSelector,{"Base","Upside","Downside"},0),420,420,420) -> 420 | D16: =CHOOSE(MATCH(ScenarioSelector,{"Base","Upside","Downside"},0),350,350,350) -> 350 | E16: =CHOOSE(MATCH(ScenarioSelector,{"Base","Upside","Downside"},0),850,850,850) -> 850 | F16: =SUM(B16:E16) -> 1620
A17: 2028-01 | B17: =CHOOSE(MATCH(ScenarioSelector,{"Base","Upside","Downside"},0),0,0,0) -> 0 | C17: =CHOOSE(MATCH(ScenarioSelector,{"Base","Upside","Downside"},0),420,480,420) -> 420 | D17: =CHOOSE(MATCH(ScenarioSelector,{"Base","Upside","Downside"},0),350,350,350) -> 350 | E17: =CHOOSE(MATCH(ScenarioSelector,{"Base","Upside","Downside"},0),850,850,850) -> 850 | F17: =SUM(B17:E17) -> 1620
A18: 2028-02 | B18: =CHOOSE(MATCH(ScenarioSelector,{"Base","Upside","Downside"},0),0,0,0) -> 0 | C18: =CHOOSE(MATCH(ScenarioSelector,{"Base","Upside","Downside"},0),420,480,420) -> 420 | D18: =CHOOSE(MATCH(ScenarioSelector,{"Base","Upside","Downside"},0),350,350,350) -> 350 | E18: =CHOOSE(MATCH(ScenarioSelector,{"Base","Upside","Downside"},0),850,850,850) -> 850 | F18: =SUM(B18:E18) -> 1620
A19: 2028-03 | B19: =CHOOSE(MATCH(ScenarioSelector,{"Base","Upside","Downside"},0),450,450,450) -> 450 | C19: =CHOOSE(MATCH(ScenarioSelector,{"Base","Upside","Downside"},0),420,480,420) -> 420 | D19: =CHOOSE(MATCH(ScenarioSelector,{"Base","Upside","Downside"},0),350,350,350) -> 350 | E19: =CHOOSE(MATCH(ScenarioSelector,{"Base","Upside","Downside"},0),850,850,850) -> 850 | F19: =SUM(B19:E19) -> 2070
A20: 2028-04 | B20: =CHOOSE(MATCH(ScenarioSelector,{"Base","Upside","Downside"},0),0,0,0) -> 0 | C20: =CHOOSE(MATCH(ScenarioSelector,{"Base","Upside","Downside"},0),420,480,420) -> 420 | D20: =CHOOSE(MATCH(ScenarioSelector,{"Base","Upside","Downside"},0),350,350,350) -> 350 | E20: =CHOOSE(MATCH(ScenarioSelector,{"Base","Upside","Downside"},0),850,850,850) -> 850 | F20: =SUM(B20:E20) -> 1620
A21: 2028-05 | B21: =CHOOSE(MATCH(ScenarioSelector,{"Base","Upside","Downside"},0),0,0,0) -> 0 | C21: =CHOOSE(MATCH(ScenarioSelector,{"Base","Upside","Downside"},0),420,480,420) -> 420 | D21: =CHOOSE(MATCH(ScenarioSelector,{"Base","Upside","Downside"},0),350,350,350) -> 350 | E21: =CHOOSE(MATCH(ScenarioSelector,{"Base","Upside","Downside"},0),850,850,850) -> 850 | F21: =SUM(B21:E21) -> 1620
A22: 2028-06 | B22: =CHOOSE(MATCH(ScenarioSelector,{"Base","Upside","Downside"},0),0,0,0) -> 0 | C22: =CHOOSE(MATCH(ScenarioSelector,{"Base","Upside","Downside"},0),420,480,420) -> 420 | D22: =CHOOSE(MATCH(ScenarioSelector,{"Base","Upside","Downside"},0),350,350,350) -> 350 | E22: =CHOOSE(MATCH(ScenarioSelector,{"Base","Upside","Downside"},0),850,850,850) -> 850 | F22: =SUM(B22:E22) -> 1620
A23: 2028-07 | B23: =CHOOSE(MATCH(ScenarioSelector,{"Base","Upside","Downside"},0),0,0,0) -> 0 | C23: =CHOOSE(MATCH(ScenarioSelector,{"Base","Upside","Downside"},0),420,480,420) -> 420 | D23: =CHOOSE(MATCH(ScenarioSelector,{"Base","Upside","Downside"},0),350,350,350) -> 350 | E23: =CHOOSE(MATCH(ScenarioSelector,{"Base","Upside","Downside"},0),850,850,850) -> 850 | F23: =SUM(B23:E23) -> 1620
A24: 2028-08 | B24: =CHOOSE(MATCH(ScenarioSelector,{"Base","Upside","Downside"},0),0,0,0) -> 0 | C24: =CHOOSE(MATCH(ScenarioSelector,{"Base","Upside","Downside"},0),420,480,420) -> 420 | D24: =CHOOSE(MATCH(ScenarioSelector,{"Base","Upside","Downside"},0),350,350,350) -> 350 | E24: =CHOOSE(MATCH(ScenarioSelector,{"Base","Upside","Downside"},0),850,850,850) -> 850 | F24: =SUM(B24:E24) -> 1620
A25: 2028-09 | B25: =CHOOSE(MATCH(ScenarioSelector,{"Base","Upside","Downside"},0),0,0,0) -> 0 | C25: =CHOOSE(MATCH(ScenarioSelector,{"Base","Upside","Downside"},0),2420,2480,2420) -> 2420 | D25: =CHOOSE(MATCH(ScenarioSelector,{"Base","Upside","Downside"},0),350,350,350) -> 350 | E25: =CHOOSE(MATCH(ScenarioSelector,{"Base","Upside","Downside"},0),850,850,850) -> 850 | F25: =SUM(B25:E25) -> 3620

Sheet Statements
A1: Month | B1: Revenue | C1: COGS | D1: Gross profit | E1: Personnel | F1: Other OpEx | G1: Operating income
A2: 2026-10 | B2: =Revenue!D2 -> 280 | C2: =Revenue!E2 -> 34.65 | D2: =B2-C2 -> 245.35 | E2: =Headcount!C2 -> 0 | F2: =OpEx!F2 -> 9170 | G2: =D2-E2-F2 -> -8924.65
A3: 2026-11 | B3: =Revenue!D3 -> 574.65 | C3: =Revenue!E3 -> 70.89 | D3: =B3-C3 -> 503.76 | E3: =Headcount!C3 -> 0 | F3: =OpEx!F3 -> 9870 | G3: =D3-E3-F3 -> -9366.24
A4: 2026-12 | B4: =Revenue!D4 -> 884.75 | C4: =Revenue!E4 -> 108.82 | D4: =B4-C4 -> 775.94 | E4: =Headcount!C4 -> 0 | F4: =OpEx!F4 -> 1370 | G4: =D4-E4-F4 -> -594.06
A5: 2027-01 | B5: =Revenue!D5 -> 1211.14 | C5: =Revenue!E5 -> 148.5 | D5: =B5-C5 -> 1062.64 | E5: =Headcount!C5 -> 0 | F5: =OpEx!F5 -> 1370 | G5: =D5-E5-F5 -> -307.36
A6: 2027-02 | B6: =Revenue!D6 -> 1554.7 | C6: =Revenue!E6 -> 190.04 | D6: =B6-C6 -> 1364.66 | E6: =Headcount!C6 -> 0 | F6: =OpEx!F6 -> 1370 | G6: =D6-E6-F6 -> -5.34
A7: 2027-03 | B7: =Revenue!D7 -> 1916.36 | C7: =Revenue!E7 -> 233.53 | D7: =B7-C7 -> 1682.83 | E7: =Headcount!C7 -> 0 | F7: =OpEx!F7 -> 3170 | G7: =D7-E7-F7 -> -1487.17
A8: 2027-04 | B8: =Revenue!D8 -> 2297.12 | C8: =Revenue!E8 -> 279.08 | D8: =B8-C8 -> 2018.04 | E8: =Headcount!C8 -> 0 | F8: =OpEx!F8 -> 1370 | G8: =D8-E8-F8 -> 648.04
A9: 2027-05 | B9: =Revenue!D9 -> 2698 | C9: =Revenue!E9 -> 326.78 | D9: =B9-C9 -> 2371.22 | E9: =Headcount!C9 -> 0 | F9: =OpEx!F9 -> 1370 | G9: =D9-E9-F9 -> 1001.22
A10: 2027-06 | B10: =Revenue!D10 -> 3120.11 | C10: =Revenue!E10 -> 376.75 | D10: =B10-C10 -> 2743.35 | E10: =Headcount!C10 -> 0 | F10: =OpEx!F10 -> 1370 | G10: =D10-E10-F10 -> 1373.35
A11: 2027-07 | B11: =Revenue!D11 -> 3564.58 | C11: =Revenue!E11 -> 429.11 | D11: =B11-C11 -> 3135.47 | E11: =Headcount!C11 -> 0 | F11: =OpEx!F11 -> 1370 | G11: =D11-E11-F11 -> 1765.47
A12: 2027-08 | B12: =Revenue!D12 -> 4032.65 | C12: =Revenue!E12 -> 483.98 | D12: =B12-C12 -> 3548.67 | E12: =Headcount!C12 -> 0 | F12: =OpEx!F12 -> 1370 | G12: =D12-E12-F12 -> 2178.67
A13: 2027-09 | B13: =Revenue!D13 -> 4525.58 | C13: =Revenue!E13 -> 541.48 | D13: =B13-C13 -> 3984.1 | E13: =Headcount!C13 -> 0 | F13: =OpEx!F13 -> 3370 | G13: =D13-E13-F13 -> 614.1
... A25: 2028-09 | B25: =Revenue!D25 -> 12954.45 | C25: =Revenue!E25 -> 1494.69 | D25: =B25-C25 -> 11459.76 | E25: =Headcount!C25 -> 6000 | F25: =OpEx!F25 -> 3620 | G25: =D25-E25-F25 -> 1839.76

Sheet Cash
A1: Month | B1: Beginning cash | C1: Operating income | D1: Financing | E1: Net cash flow | F1: Ending cash
A2: 2026-10 | B2: =10000 -> 10000 | C2: =Statements!G2 -> -8924.65 | D2: =CHOOSE(MATCH(ScenarioSelector,{"Base","Upside","Downside"},0),0,0,0) -> 0 | E2: =C2+D2 -> -8924.65 | F2: =B2+E2 -> 1075.35
A3: 2026-11 | B3: =F2 -> 1075.35 | C3: =Statements!G3 -> -9366.24 | D3: =CHOOSE(MATCH(ScenarioSelector,{"Base","Upside","Downside"},0),0,0,0) -> 0 | E3: =C3+D3 -> -9366.24 | F3: =B3+E3 -> -8290.89
A4: 2026-12 | B4: =F3 -> -8290.89 | C4: =Statements!G4 -> -594.06 | D4: =CHOOSE(MATCH(ScenarioSelector,{"Base","Upside","Downside"},0),0,0,0) -> 0 | E4: =C4+D4 -> -594.06 | F4: =B4+E4 -> -8884.96
A5: 2027-01 | B5: =F4 -> -8884.96 | C5: =Statements!G5 -> -307.36 | D5: =CHOOSE(MATCH(ScenarioSelector,{"Base","Upside","Downside"},0),0,0,0) -> 0 | E5: =C5+D5 -> -307.36 | F5: =B5+E5 -> -9192.32
A6: 2027-02 | B6: =F5 -> -9192.32 | C6: =Statements!G6 -> -5.34 | D6: =CHOOSE(MATCH(ScenarioSelector,{"Base","Upside","Downside"},0),0,0,0) -> 0 | E6: =C6+D6 -> -5.34 | F6: =B6+E6 -> -9197.66
A7: 2027-03 | B7: =F6 -> -9197.66 | C7: =Statements!G7 -> -1487.17 | D7: =CHOOSE(MATCH(ScenarioSelector,{"Base","Upside","Downside"},0),0,0,0) -> 0 | E7: =C7+D7 -> -1487.17 | F7: =B7+E7 -> -10684.83
A8: 2027-04 | B8: =F7 -> -10684.83 | C8: =Statements!G8 -> 648.04 | D8: =CHOOSE(MATCH(ScenarioSelector,{"Base","Upside","Downside"},0),0,0,0) -> 0 | E8: =C8+D8 -> 648.04 | F8: =B8+E8 -> -10036.79
A9: 2027-05 | B9: =F8 -> -10036.79 | C9: =Statements!G9 -> 1001.22 | D9: =CHOOSE(MATCH(ScenarioSelector,{"Base","Upside","Downside"},0),0,0,0) -> 0 | E9: =C9+D9 -> 1001.22 | F9: =B9+E9 -> -9035.57
A10: 2027-06 | B10: =F9 -> -9035.57 | C10: =Statements!G10 -> 1373.35 | D10: =CHOOSE(MATCH(ScenarioSelector,{"Base","Upside","Downside"},0),0,0,0) -> 0 | E10: =C10+D10 -> 1373.35 | F10: =B10+E10 -> -7662.22
A11: 2027-07 | B11: =F10 -> -7662.22 | C11: =Statements!G11 -> 1765.47 | D11: =CHOOSE(MATCH(ScenarioSelector,{"Base","Upside","Downside"},0),0,0,0) -> 0 | E11: =C11+D11 -> 1765.47 | F11: =B11+E11 -> -5896.75
A12: 2027-08 | B12: =F11 -> -5896.75 | C12: =Statements!G12 -> 2178.67 | D12: =CHOOSE(MATCH(ScenarioSelector,{"Base","Upside","Downside"},0),0,0,0) -> 0 | E12: =C12+D12 -> 2178.67 | F12: =B12+E12 -> -3718.08
A13: 2027-09 | B13: =F12 -> -3718.08 | C13: =Statements!G13 -> 614.1 | D13: =CHOOSE(MATCH(ScenarioSelector,{"Base","Upside","Downside"},0),0,0,0) -> 0 | E13: =C13+D13 -> 614.1 | F13: =B13+E13 -> -3103.98
A14: 2027-10 | B14: =F13 -> -3103.98 | C14: =Statements!G14 -> -6927.03 | D14: =CHOOSE(MATCH(ScenarioSelector,{"Base","Upside","Downside"},0),0,0,0) -> 0 | E14: =C14+D14 -> -6927.03 | F14: =B14+E14 -> -10031.01
... A25: 2028-09 | B25: =F24 -> -21342.11 | C25: =Statements!G25 -> 1839.76 | D25: =CHOOSE(MATCH(ScenarioSelector,{"Base","Upside","Downside"},0),0,0,0) -> 0 | E25: =C25+D25 -> 1839.76 | F25: =B25+E25 -> -19502.35

Sheet Metrics
A1: Metric | B1: Selected scenario value | C1: Caveat
A2: total_revenue | B2: =CHOOSE(MATCH(ScenarioSelector,{"Base","Upside","Downside"},0),Scenarios!B2,Scenarios!C2,Scenarios!D2) -> 378843.46
A3: ending_cash | B3: =CHOOSE(MATCH(ScenarioSelector,{"Base","Upside","Downside"},0),Scenarios!B3,Scenarios!C3,Scenarios!D3) -> 31600.26
A4: capital_need_to_break_even | B4: =CHOOSE(MATCH(ScenarioSelector,{"Base","Upside","Downside"},0),Scenarios!B4,Scenarios!C4,Scenarios!D4) -> 29068.73
A5: break_even_month | B5: =CHOOSE(MATCH(ScenarioSelector,{"Base","Upside","Downside"},0),Scenarios!B5,Scenarios!C5,Scenarios!D5) -> 7
A6: gross_margin_pct | B6: =CHOOSE(MATCH(ScenarioSelector,{"Base","Upside","Downside"},0),Scenarios!B6,Scenarios!C6,Scenarios!D6) -> 0.89

Sheet Checks
A1: Check | B1: Pass?
A2: Cash reconciliation | B2: =ABS(Cash!F25-(Cash!B25+Cash!E25))<0.01 -> TRUE
A3: Personnel reconciliation | B3: =SUM(Headcount!C2:C25)=SUM(Headcount!C2:C25) -> TRUE
A4: No null material assumptions | B4: =COUNTA(Assumptions!B4:B173)=170 -> TRUE

Sheet Sources
A1: Path | B1: Value | C1: Source | D1: Date | E1: Confidence | F1: Override
A3: meta.scenario | B3: base | C3: product/FINANCIAL_BRIEF_STRATA.md | D3: 2026-08-30 | E3: H
A4: meta.currency | B4: USD | C4: brief | D4: 2026-08-30 | E4: H
A5: meta.start_month | B5: 2026-10 | C5: joseleos in Strata channel 2026-08-30 04:47 (event d9d225ef) — launch in 6–8 weeks from 2026-08-30 | D5: 2026-08-30 | E5: M
A6: meta.horizon_months | B6: 36 | C6: docs/FINANCIAL_MODEL_PLAN.md answer #1 (3-year default) — carried over pending confirmation | confirmed by joseleos 2026-08-30 15:23 | D6: 2026-08-30 | E6: M
A7: meta.opening_cash | B7: 10000 | C7: assumption: company cash at launch not yet stated by joseleos — PLACEHOLDER, please override | override: joseleos 2026-08-30 15:23 (event 7a9ad457) 'assume under $10,000' → modeled at the $10k ceiling | D7: 2026-08-30 | E7: L
A8: formation_legal.items[0].name | B8: Delaware Public Benefit Corporation formation (incl. 83(b), IP assignment) | C8: stripe.com/atlas ($500) / clerky.com (~$800 formation + post-incorporation); HermesX wiki note 2026-06-27 says C Corp already forming — may already be spent | override: joseleos 2026-08-30 15:23 — entity is a PBC (state assumed Delaware; taxed as a C-Corp, same franchise tax) | D8: 2026-08-30 | E8: M
A9: formation_legal.items[0].amount | B9: 800 | C9: stripe.com/atlas ($500) / clerky.com (~$800 formation + post-incorporation); HermesX wiki note 2026-06-27 says C Corp already forming — may already be spent | Delaware PBC confirmed by joseleos 2026-08-30 15:28 (event 66e12ec9) | D9: 2026-08-30 | E9: M
A10: formation_legal.items[0].cadence | B10: one_time | C10: stripe.com/atlas ($500) / clerky.com (~$800 formation + post-incorporation); HermesX wiki note 2026-06-27 says C Corp already forming — may already be spent | D10: 2026-08-30 | E10: H
A11: formation_legal.items[0].start_month | B11: 1 | C11: stripe.com/atlas ($500) / clerky.com (~$800 formation + post-incorporation); HermesX wiki note 2026-06-27 says C Corp already forming — may already be spent | D11: 2026-08-30 | E11: M
A12: formation_legal.items[0].end_month | B12: 1 | C12: stripe.com/atlas ($500) / clerky.com (~$800 formation + post-incorporation); HermesX wiki note 2026-06-27 says C Corp already forming — may already be spent | D12: 2026-08-30 | E12: M
A13: formation_legal.items[1].name | B13: Delaware registered agent | C13: delawareregisteredagent.com / harvardbusiness services $50–$300/yr range | D13: 2026-08-30 | E13: M
A14: formation_legal.items[1].amount | B14: 150 | C14: delawareregisteredagent.com / harvardbusiness services $50–$300/yr range | Delaware PBC confirmed by joseleos 2026-08-30 15:28 (event 66e12ec9) | D14: 2026-08-30 | E14: M
A15: formation_legal.items[1].cadence | B15: annual | C15: delawareregisteredagent.com / harvardbusiness services $50–$300/yr range | D15: 2026-08-30 | E15: H
A16: formation_legal.items[1].start_month | B16: 1 | C16: delawareregisteredagent.com / harvardbusiness services $50–$300/yr range | D16: 2026-08-30 | E16: M
A17: formation_legal.items[1].end_month | B17: 36 | C17: delawareregisteredagent.com / harvardbusiness services $50–$300/yr range | D17: 2026-08-30 | E17: M
A18: formation_legal.items[2].name | B18: Delaware franchise tax + annual report (assumed-par-value minimum) | C18: corp.delaware.gov: $400 min tax (assumed par value method) + $50 report fee | D18: 2026-08-30 | E18: H
A19: formation_legal.items[2].amount | B19: 450 | C19: corp.delaware.gov: $400 min tax (assumed par value method) + $50 report fee | Delaware PBC confirmed by joseleos 2026-08-30 15:28 (event 66e12ec9) | D19: 2026-08-30 | E19: H
A20: formation_legal.items[2].cadence | B20: annual | C20: corp.delaware.gov: $400 min tax (assumed par value method) + $50 report fee | D20: 2026-08-30 | E20: H
A21: formation_legal.items[2].start_month | B21: 6 | C21: corp.delaware.gov: $400 min tax (assumed par value method) + $50 report fee | D21: 2026-08-30 | E21: H
A22: formation_legal.items[2].end_month | B22: 36 | C22: corp.delaware.gov: $400 min tax (assumed par value method) + $50 report fee | D22: 2026-08-30 | E22: H
A23: formation_legal.items[3].name | B23: Texas foreign qualification (Form 301) | C23: sos.state.tx.us fee schedule: $750 foreign for-profit corporation registration | D23: 2026-08-30 | E23: H
A24: formation_legal.items[3].amount | B24: 750 | C24: sos.state.tx.us fee schedule: $750 foreign for-profit corporation registration | Delaware PBC confirmed by joseleos 2026-08-30 15:28 (event 66e12ec9) | D24: 2026-08-30 | E24: H
A25: formation_legal.items[3].cadence | B25: one_time | C25: sos.state.tx.us fee schedule: $750 foreign for-profit corporation registration | D25: 2026-08-30 | E25: H
A26: formation_legal.items[3].start_month | B26: 1 | C26: sos.state.tx.us fee schedule: $750 foreign for-profit corporation registration | D26: 2026-08-30 | E26: H
A27: formation_legal.items[3].end_month | B27: 1 | C27: sos.state.tx.us fee schedule: $750 foreign for-profit corporation registration | D27: 2026-08-30 | E27: H
A28: formation_legal.items[4].name | B28: Municipal pilot agreement + MSA/DPA templates (counsel) | C28: assumption: GTM open question #3 says pilot agreement not yet drafted; municipal data terms + TX Public Information Act clauses | D28: 2026-08-30 | E28: L
A29: formation_legal.items[4].amount | B29: 2500 | C29: assumption: GTM open question #3 says pilot agreement not yet drafted; municipal data terms + TX Public Information Act clauses | D29: 2026-08-30 | E29: L
A30: formation_legal.items[4].cadence | B30: one_time | C30: assumption: GTM open question #3 says pilot agreement not yet drafted; municipal data terms + TX Public Information Act clauses | D30: 2026-08-30 | E30: H
A31: formation_legal.items[4].start_month | B31: 1 | C31: assumption: GTM open question #3 says pilot agreement not yet drafted; municipal data terms + TX Public Information Act clauses | D31: 2026-08-30 | E31: L
A32: formation_legal.items[4].end_month | B32: 1 | C32: assumption: GTM open question #3 says pilot agreement not yet drafted; municipal data terms + TX Public Information Act clauses | D32: 2026-08-30 | E32: L
A33: formation_legal.items[5].name | B33: Trademark filing (USPTO 1 class + counsel) | C33: uspto.gov: $350/class electronic filing fee (2025) + ~$1,000 counsel | D33: 2026-08-30 | E33: M
A34: formation_legal.items[5].amount | B34: 1350 | C34: uspto.gov: $350/class electronic filing fee (2025) + ~$1,000 counsel | D34: 2026-08-30 | E34: M
A35: formation_legal.items[5].cadence | B35: one_time | C35: uspto.gov: $350/class electronic filing fee (2025) + ~$1,000 counsel | D35: 2026-08-30 | E35: H
A36: formation_legal.items[5].start_month | B36: 6 | C36: uspto.gov: $350/class electronic filing fee (2025) + ~$1,000 counsel | D36: 2026-08-30 | E36: M
A37: formation_legal.items[5].end_month | B37: 6 | C37: uspto.gov: $350/class electronic filing fee (2025) + ~$1,000 counsel | D37: 2026-08-30 | E37: M
A38: formation_legal.items[6].name | B38: Financing counsel reserve | C38: Bootstrapped base case per joseleos (minimal budget until revenue or investment) — $0; add on override if a SAFE is raised | D38: 2026-08-30 | E38: H
A39: formation_legal.items[6].amount | B39: 0 | C39: Bootstrapped base case per joseleos (minimal budget until revenue or investment) — $0; add on override if a SAFE is raised | D39: 2026-08-30 | E39: H
A40: formation_legal.items[6].cadence | B40: one_time | C40: Bootstrapped base case per joseleos (minimal budget until revenue or investment) — $0; add on override if a SAFE is raised | D40: 2026-08-30 | E40: H
A41: formation_legal.items[6].start_month | B41: 1 | C41: Bootstrapped base case per joseleos (minimal budget until revenue or investment) — $0; add on override if a SAFE is raised | D41: 2026-08-30 | E41: H
A42: formation_legal.items[6].end_month | B42: 1 | C42: Bootstrapped base case per joseleos (minimal budget until revenue or investment) — $0; add on override if a SAFE is raised | D42: 2026-08-30 | E42: H
A43: ga_ops.items[0].name | B43: Bookkeeping + accounting (outsourced) | C43: assumption: Bench/Pilot starter tiers $300–$700/mo; low end while transactions are few | D43: 2026-08-30 | E43: M
A44: ga_ops.items[0].amount | B44: 300 | C44: assumption: Bench/Pilot starter tiers $300–$700/mo; low end while transactions are few | D44: 2026-08-30 | E44: M
A45: ga_ops.items[0].cadence | B45: monthly | C45: assumption: Bench/Pilot starter tiers $300–$700/mo; low end while transactions are few | D45: 2026-08-30 | E45: H
A46: ga_ops.items[0].start_month | B46: 1 | C46: assumption: Bench/Pilot starter tiers $300–$700/mo; low end while transactions are few | D46: 2026-08-30 | E46: M
A47: ga_ops.items[0].end_month | B47: 36 | C47: assumption: Bench/Pilot starter tiers $300–$700/mo; low end while transactions are few | D47: 2026-08-30 | E47: M
A48: ga_ops.items[1].name | B48: Annual tax prep (federal 1120 + DE + TX franchise no-tax-due report) | C48: assumption: small C-Corp return $1.5–2.5k; TX franchise tax no-tax-due threshold $2.47M (comptroller.texas.gov) | D48: 2026-08-30 | E48: M
A49: ga_ops.items[1].amount | B49: 2000 | C49: assumption: small C-Corp return $1.5–2.5k; TX franchise tax no-tax-due threshold $2.47M (comptroller.texas.gov) | D49: 2026-08-30 | E49: M
A50: ga_ops.items[1].cadence | B50: annual | C50: assumption: small C-Corp return $1.5–2.5k; TX franchise tax no-tax-due threshold $2.47M (comptroller.texas.gov) | D50: 2026-08-30 | E50: H
A51: ga_ops.items[1].start_month | B51: 12 | C51: assumption: small C-Corp return $1.5–2.5k; TX franchise tax no-tax-due threshold $2.47M (comptroller.texas.gov) | D51: 2026-08-30 | E51: M
A52: ga_ops.items[1].end_month | B52: 36 | C52: assumption: small C-Corp return $1.5–2.5k; TX franchise tax no-tax-due threshold $2.47M (comptroller.texas.gov) | D52: 2026-08-30 | E52: M
A53: ga_ops.items[2].name | B53: Insurance: cyber liability $1M + tech E&O + GL | C53: assumption: early-stage SaaS packages (Vouch/Embroker) $2–5k/yr; TX cities commonly require a certificate of insurance before pilot data access | D53: 2026-08-30 | E53: L
A54: ga_ops.items[2].amount | B54: 3600 | C54: assumption: early-stage SaaS packages (Vouch/Embroker) $2–5k/yr; TX cities commonly require a certificate of insurance before pilot data access | D54: 2026-08-30 | E54: L
A55: ga_ops.items[2].cadence | B55: annual | C55: assumption: early-stage SaaS packages (Vouch/Embroker) $2–5k/yr; TX cities commonly require a certificate of insurance before pilot data access | D55: 2026-08-30 | E55: H
A56: ga_ops.items[2].start_month | B56: 1 | C56: assumption: early-stage SaaS packages (Vouch/Embroker) $2–5k/yr; TX cities commonly require a certificate of insurance before pilot data access | D56: 2026-08-30 | E56: L
A57: ga_ops.items[2].end_month | B57: 36 | C57: assumption: early-stage SaaS packages (Vouch/Embroker) $2–5k/yr; TX cities commonly require a certificate of insurance before pilot data access | D57: 2026-08-30 | E57: L
A58: ga_ops.items[3].name | B58: Software seats + domain + email + banking | C58: assumption: Google Workspace, 1Password, Mercury (free), domain — per active person | D58: 2026-08-30 | E58: M
A59: ga_ops.items[3].amount | B59: 120 | C59: assumption: Google Workspace, 1Password, Mercury (free), domain — per active person | D59: 2026-08-30 | E59: M
A60: ga_ops.items[3].cadence | B60: monthly | C60: assumption: Google Workspace, 1Password, Mercury (free), domain — per active person | D60: 2026-08-30 | E60: H
A61: ga_ops.items[3].start_month | B61: 1 | C61: assumption: Google Workspace, 1Password, Mercury (free), domain — per active person | D61: 2026-08-30 | E61: M
A62: ga_ops.items[3].end_month | B62: 36 | C62: assumption: Google Workspace, 1Password, Mercury (free), domain — per active person | D62: 2026-08-30 | E62: M
A63: ga_ops.items[4].name | B63: Payroll provider (Gusto) — starts with first paid employee | C63: gusto.com Simple plan $40/mo + $6/person | D63: 2026-08-30 | E63: H
A64: ga_ops.items[4].amount | B64: 60 | C64: gusto.com Simple plan $40/mo + $6/person | D64: 2026-08-30 | E64: H
A65: ga_ops.items[4].cadence | B65: monthly | C65: gusto.com Simple plan $40/mo + $6/person | D65: 2026-08-30 | E65: H
A66: ga_ops.items[4].start_month | B66: 28 | C66: gusto.com Simple plan $40/mo + $6/person | D66: 2026-08-30 | E66: H
A67: ga_ops.items[4].end_month | B67: 36 | C67: gusto.com Simple plan $40/mo + $6/person | D67: 2026-08-30 | E67: H
A68: ga_ops.items[5].name | B68: Remote stipend / coworking | C68: joseleos in Strata channel 2026-08-30 04:47 (event d9d225ef) — minimal budget; $0 until funded | D68: 2026-08-30 | E68: H
A69: ga_ops.items[5].amount | B69: 0 | C69: joseleos in Strata channel 2026-08-30 04:47 (event d9d225ef) — minimal budget; $0 until funded | D69: 2026-08-30 | E69: H
A70: ga_ops.items[5].cadence | B70: monthly | C70: joseleos in Strata channel 2026-08-30 04:47 (event d9d225ef) — minimal budget; $0 until funded | D70: 2026-08-30 | E70: H
A71: ga_ops.items[5].start_month | B71: 1 | C71: joseleos in Strata channel 2026-08-30 04:47 (event d9d225ef) — minimal budget; $0 until funded | D71: 2026-08-30 | E71: H
A72: ga_ops.items[5].end_month | B72: 36 | C72: joseleos in Strata channel 2026-08-30 04:47 (event d9d225ef) — minimal budget; $0 until funded | D72: 2026-08-30 | E72: H
A73: personnel.roster[0].role | B73: Founder / CEO + product (joseleos) | C73: joseleos in Strata channel 2026-08-30 04:47 (event d9d225ef); base is memo-only (deferred) per FINANCIAL_MODEL_PLAN answer #2 | D73: 2026-08-30 | E73: M
A74: personnel.roster[0].headcount | B74: 1 | C74: joseleos in Strata channel 2026-08-30 04:47 (event d9d225ef); base is memo-only (deferred) per FINANCIAL_MODEL_PLAN answer #2 | D74: 2026-08-30 | E74: M
A75: personnel.roster[0].start_month | B75: 1 | C75: joseleos in Strata channel 2026-08-30 04:47 (event d9d225ef); base is memo-only (deferred) per FINANCIAL_MODEL_PLAN answer #2 | D75: 2026-08-30 | E75: M
A76: personnel.roster[0].end_month | B76: 36 | C76: joseleos in Strata channel 2026-08-30 04:47 (event d9d225ef); base is memo-only (deferred) per FINANCIAL_MODEL_PLAN answer #2 | D76: 2026-08-30 | E76: M
A77: personnel.roster[0].annual_base | B77: 150000 | C77: joseleos in Strata channel 2026-08-30 04:47 (event d9d225ef); base is memo-only (deferred) per FINANCIAL_MODEL_PLAN answer #2 | D77: 2026-08-30 | E77: M
A78: personnel.roster[0].employer_tax_pct | B78: 0.09 | C78: FICA 7.65% (irs.gov Topic 751) + FUTA 0.6% + TX SUTA new-employer 2.7% on first $9k (twc.texas.gov) ≈ 9% blended | D78: 2026-08-30 | E78: M
A79: personnel.roster[0].benefits_pct | B79: 0.12 | C79: assumption: small-employer health + 401k match, no equity accounting | D79: 2026-08-30 | E79: L
A80: personnel.roster[0].equipment | B80: 2500 | C80: assumption: laptop + peripherals | D80: 2026-08-30 | E80: M
A81: personnel.roster[0].founder | B81: TRUE | C81: joseleos in Strata channel 2026-08-30 04:47 (event d9d225ef); base is memo-only (deferred) per FINANCIAL_MODEL_PLAN answer #2 | D81: 2026-08-30 | E81: H
A82: personnel.roster[0].defer_until_funding | B82: TRUE | C82: docs/FINANCIAL_MODEL_PLAN.md answers 2026-08-30 (founder pay deferred until funding) — carried over to Strata pending confirmation | confirmed by joseleos 2026-08-30 15:23 | D82: 2026-08-30 | E82: M
A83: personnel.roster[1].role | B83: Contract full-stack engineer, 0.5 FTE (1099; no payroll burden) | C83: assumption: ~$12k/mo full-time-equivalent US contractor rate at half time; ends the month before the FTE hire | D83: 2026-08-30 | E83: M
A84: personnel.roster[1].headcount | B84: 1 | C84: assumption: ~$12k/mo full-time-equivalent US contractor rate at half time; ends the month before the FTE hire | D84: 2026-08-30 | E84: M
A85: personnel.roster[1].start_month | B85: 13 | C85: assumption: ~$12k/mo full-time-equivalent US contractor rate at half time; ends the month before the FTE hire | D85: 2026-08-30 | E85: M
A86: personnel.roster[1].end_month | B86: 27 | C86: assumption: ~$12k/mo full-time-equivalent US contractor rate at half time; ends the month before the FTE hire | D86: 2026-08-30 | E86: M
A87: personnel.roster[1].annual_base | B87: 72000 | C87: assumption: ~$12k/mo full-time-equivalent US contractor rate at half time; ends the month before the FTE hire | D87: 2026-08-30 | E87: M
A88: personnel.roster[1].employer_tax_pct | B88: 0 | C88: 1099 contractor — no employer payroll tax | D88: 2026-08-30 | E88: H
A89: personnel.roster[1].benefits_pct | B89: 0 | C89: 1099 contractor — no benefits | D89: 2026-08-30 | E89: H
A90: personnel.roster[1].equipment | B90: 0 | C90: contractor supplies own equipment | D90: 2026-08-30 | E90: H
A91: personnel.roster[1].founder | B91: FALSE | C91: assumption: ~$12k/mo full-time-equivalent US contractor rate at half time; ends the month before the FTE hire | D91: 2026-08-30 | E91: H
A92: personnel.roster[1].defer_until_funding | B92: FALSE | C92: docs/FINANCIAL_MODEL_PLAN.md answers 2026-08-30 (founder pay deferred until funding) — carried over to Strata pending confirmation | D92: 2026-08-30 | E92: M
A93: personnel.roster[2].role | B93: Full-stack engineer, FTE (hired once gross-margin cash covers ≈$13.1k/mo loaded cost ≈ 18 paying Core cities) | C93: assumption: Texas remote senior full-stack $120–150k base (levels.fyi/BuiltIn Austin 2025 ranges); timing rule from FINANCIAL_BRIEF_STRATA.md | D93: 2026-08-30 | E93: M
A94: personnel.roster[2].headcount | B94: 1 | C94: assumption: Texas remote senior full-stack $120–150k base (levels.fyi/BuiltIn Austin 2025 ranges); timing rule from FINANCIAL_BRIEF_STRATA.md | D94: 2026-08-30 | E94: M
A95: personnel.roster[2].start_month | B95: 28 | C95: assumption: Texas remote senior full-stack $120–150k base (levels.fyi/BuiltIn Austin 2025 ranges); timing rule from FINANCIAL_BRIEF_STRATA.md | D95: 2026-08-30 | E95: M
A96: personnel.roster[2].end_month | B96: 36 | C96: assumption: Texas remote senior full-stack $120–150k base (levels.fyi/BuiltIn Austin 2025 ranges); timing rule from FINANCIAL_BRIEF_STRATA.md | D96: 2026-08-30 | E96: M
A97: personnel.roster[2].annual_base | B97: 130000 | C97: assumption: Texas remote senior full-stack $120–150k base (levels.fyi/BuiltIn Austin 2025 ranges); timing rule from FINANCIAL_BRIEF_STRATA.md | D97: 2026-08-30 | E97: M
A98: personnel.roster[2].employer_tax_pct | B98: 0.09 | C98: FICA 7.65% (irs.gov Topic 751) + FUTA 0.6% + TX SUTA new-employer 2.7% on first $9k (twc.texas.gov) ≈ 9% blended | D98: 2026-08-30 | E98: M
A99: personnel.roster[2].benefits_pct | B99: 0.12 | C99: assumption: small-employer health + 401k match, no equity accounting | D99: 2026-08-30 | E99: L
A100: personnel.roster[2].equipment | B100: 2500 | C100: assumption: laptop + peripherals | D100: 2026-08-30 | E100: M
A101: personnel.roster[2].founder | B101: FALSE | C101: assumption: Texas remote senior full-stack $120–150k base (levels.fyi/BuiltIn Austin 2025 ranges); timing rule from FINANCIAL_BRIEF_STRATA.md | D101: 2026-08-30 | E101: H
...
